colormap_tool/__init__.py
colormap_tool/_cmps.py
colormap_tool/_cv.py
colormap_tool/_mpl.py
colormap_tool/resources/cv_colormaps.pickle
colormap_tool/resources/mpl_colormaps.pickle
colormap_tool-1.1.0.dist-info/licenses/LICENSE
colormap_tool-1.1.0.dist-info/METADATA
colormap_tool-1.1.0.dist-info/WHEEL
colormap_tool-1.1.0.dist-info/top_level.txt
colormap_tool-1.1.0.dist-info/RECORD
