Metadata-Version: 2.4
Name: colormap-tool
Version: 1.1.0
Summary: A Colormap Tool package to convert cmps between cv and mpl.
Author-email: Meridian Innovation <info@meridianinno.com>
Project-URL: Homepage, https://MeridianInnovation.github.io/colormap-tool/
Project-URL: Repository, https://github.com/MeridianInnovation/colormap-tool
Project-URL: Documentation, https://MeridianInnovation.github.io/colormap-tool/
Keywords: python
Classifier: Intended Audience :: Developers
Classifier: Programming Language :: Python
Classifier: Programming Language :: Python :: 3
Classifier: Programming Language :: Python :: 3.9
Classifier: Programming Language :: Python :: 3.10
Classifier: Programming Language :: Python :: 3.11
Classifier: Programming Language :: Python :: 3.12
Classifier: Topic :: Software Development :: Libraries :: Python Modules
Requires-Python: <4.0,>=3.9
License-File: LICENSE
Requires-Dist: numpy>=2.0.2
Provides-Extra: optional
Requires-Dist: matplotlib>=3.9.4; extra == "optional"
Requires-Dist: opencv-python>=4.11.0.86; extra == "optional"
Dynamic: license-file
